moco/__init__.py
moco_python-0.0.2.dist-info/METADATA
moco_python-0.0.2.dist-info/WHEEL
moco_python-0.0.2.dist-info/licenses/LICENSE
moco_python-0.0.2.dist-info/RECORD
