Metadata-Version: 2.4
Name: moco-python
Version: 0.0.2
Summary: Object-oriented command line interface (CLI) framework for Python. 
Project-URL: Documentation, https://moco.monkeyhbd.com/
Project-URL: Source, https://github.com/monkeyhbd/moco/
Author-email: Monkeyhbd <monkeyhbd@outlook.com>
License-Expression: LGPL-3.0-or-later
License-File: LICENSE
Classifier: Intended Audience :: Developers
Classifier: Operating System :: OS Independent
Classifier: Programming Language :: Python :: 3
Requires-Python: >=3.9
